panglib/__init__.py
panglib/lexer.py
panglib/pangdisp.py
panglib/pangfunc.py
panglib/parser.py
panglib/stack.py
panglib/utils.py
pedlib/__init__.py
pedlib/acthand.py
pedlib/acthand2.py
pedlib/keyhand.py
pedlib/keywords.py
pedlib/leven.py
pedlib/pedai.py
pedlib/pedbuffs.py
pedlib/pedcal.py
pedlib/pedcanv.py
pedlib/pedcolor.py
pedlib/pedconfig.py
pedlib/peddlg.py
pedlib/peddoc.py
pedlib/peddraw.py
pedlib/pedfind.py
pedlib/pedfont.py
pedlib/pedgoto.py
pedlib/pedidle.py
pedlib/pedlcmd.py
pedlib/pedlog.py
pedlib/pedmenu.py
pedlib/pedmisc.py
pedlib/pednotes.py
pedlib/pedobjs.py
pedlib/pedofd.py
pedlib/pedoline.py
pedlib/pedplug.py
pedlib/pedspell.py
pedlib/pedsql.py
pedlib/pedstruct.py
pedlib/pedtask.py
pedlib/pedtdlg.py
pedlib/pedthread.py
pedlib/pedtts.py
pedlib/pedui.py
pedlib/pedundo.py
pedlib/peduni.py
pedlib/pedutil.py
pedlib/pedweb.py
pedlib/pedwin.py
pedlib/pedxtnd.py
pedlib/pedync.py
pedlib/setupdlg.py
pedlib/stack.py
pedlib/data/KEYS
pedlib/data/KEYS.TXT
pedlib/data/KEYS.old
pedlib/data/PyGObject.txt
pedlib/data/QHELP
pedlib/data/__init__.py
pedlib/data/spell.txt
pedlib/data/test.Makefile
pedlib/data/test.S
pedlib/data/test.c
pedlib/data/test.py
pedlib/docs/acthand.html
pedlib/docs/keyhand.html
pedlib/docs/keywords.html
pedlib/docs/leven.html
pedlib/docs/pedbuffs.html
pedlib/docs/pedcal.html
pedlib/docs/pedcanv.html
pedlib/docs/pedcolor.html
pedlib/docs/pedconfig.html
pedlib/docs/peddlg.html
pedlib/docs/peddoc.html
pedlib/docs/peddraw.html
pedlib/docs/pedfind.html
pedlib/docs/pedfont.html
pedlib/docs/pedgoto.html
pedlib/docs/pedlcmd.html
pedlib/docs/pedlog.html
pedlib/docs/pedmenu.html
pedlib/docs/pedmisc.html
pedlib/docs/pednotes.html
pedlib/docs/pedobjs.html
pedlib/docs/pedofd.html
pedlib/docs/pedoline.html
pedlib/docs/pedplug.html
pedlib/docs/pedspell.html
pedlib/docs/pedsql.html
pedlib/docs/pedstruct.html
pedlib/docs/pedtask.html
pedlib/docs/pedtdlg.html
pedlib/docs/pedthread.html
pedlib/docs/pedtts.html
pedlib/docs/pedui.html
pedlib/docs/pedundo.html
pyedpro-3.9.2.dist-info/licenses/LICENSE
pyedpro-3.9.2.dist-info/licenses/LICENSE.backup
pyedpro-3.9.2.dist-info/METADATA
pyedpro-3.9.2.dist-info/WHEEL
pyedpro-3.9.2.dist-info/entry_points.txt
pyedpro-3.9.2.dist-info/top_level.txt
pyedpro-3.9.2.dist-info/RECORD
