Metadata-Version: 2.4
Name: pyedpro
Version: 3.9.2
Summary: High power editor in python.
Home-page: https://github.com/pglen/pyedpro
Author: Peter Glen
Author-email: peterglen99@gmail.com
Classifier: Programming Language :: Python :: 3
Classifier: License :: OSI Approved :: MIT License
Classifier: Operating System :: OS Independent
Requires-Python: >=3
License-File: LICENSE
License-File: LICENSE.backup
Requires-Dist: pyvpacker
Requires-Dist: pydbase
Requires-Dist: pyvguicom
Requires-Dist: pygobject==3.50.1
Dynamic: author
Dynamic: author-email
Dynamic: classifier
Dynamic: description
Dynamic: description-content-type
Dynamic: home-page
Dynamic: license-file
Dynamic: requires-dist
Dynamic: requires-python
Dynamic: summary
